kbitfont/__init__.py
kbitfont/error.py
kbitfont/font.py
kbitfont/glyph.py
kbitfont/names.py
kbitfont/props.py
kbitfont/utils/__init__.py
kbitfont/utils/base64.py
kbitfont/utils/kbits.py
kbitfont/utils/kbitx.py
kbitfont/utils/stream.py
kbitfont-0.0.6.dist-info/WHEEL
kbitfont-0.0.6.dist-info/METADATA
kbitfont-0.0.6.dist-info/RECORD
