Metadata-Version: 2.4
Name: kbitfont
Version: 0.0.6
Summary: A library for parsing Bits'N'Picas native save format files ('.kbits' and '.kbitx')
Keywords: font,kbits,kbitx
Author: TakWolf
License-Expression: MIT
Classifier: Programming Language :: Python :: 3
Classifier: Programming Language :: Python :: 3.10
Classifier: Programming Language :: Python :: 3.11
Classifier: Programming Language :: Python :: 3.12
Classifier: Programming Language :: Python :: 3.13
Classifier: Programming Language :: Python :: 3.14
Classifier: License :: OSI Approved :: MIT License
Classifier: Operating System :: OS Independent
Requires-Dist: lxml>=6.0.2
Maintainer: TakWolf
Requires-Python: >=3.10
Project-URL: Homepage, https://github.com/TakWolf/kbitfont-python
Project-URL: Issues, https://github.com/TakWolf/kbitfont-python/issues
Project-URL: Source, https://github.com/TakWolf/kbitfont-python
